README.md
setup.py
telegram_collector/__init__.py
telegram_collector/__main__.py
telegram_collector/util.py
telegram_collector.egg-info/PKG-INFO
telegram_collector.egg-info/SOURCES.txt
telegram_collector.egg-info/dependency_links.txt
telegram_collector.egg-info/entry_points.txt
telegram_collector.egg-info/requires.txt
telegram_collector.egg-info/top_level.txt