Metadata-Version: 2.1
Name: telegram_collector
Version: 0.2.3
Summary: 收集电报群组的视频图片消息
Home-page: https://github.com/fengleicn/telegram_collector
Author: fengleicn
Author-email: fengleisemail@gmail.com
Requires-Dist: telethon
Requires-Dist: python_socks
Requires-Dist: async_timeout
